cosbos/__init__.py
cosbos/blockage.py
cosbos/ltm.py
cosbos/reflection.py
cosbos-1.0.1.dist-info/METADATA
cosbos-1.0.1.dist-info/WHEEL
cosbos-1.0.1.dist-info/top_level.txt
cosbos-1.0.1.dist-info/RECORD
