Metadata-Version: 2.4
Name: cosbos
Version: 1.0.1
Summary: COlor-Sensor-Based Occupancy Sensing
Home-page: https://github.com/wq2012/COSBOS
Author: Quan Wang
Classifier: Programming Language :: Python :: 3
Classifier: License :: OSI Approved :: BSD License
Classifier: Operating System :: OS Independent
Requires-Python: >=3.6
Requires-Dist: numpy
Requires-Dist: scipy
Requires-Dist: scikit-learn
Requires-Dist: cvxpy
Dynamic: author
Dynamic: classifier
Dynamic: description
Dynamic: description-content-type
Dynamic: home-page
Dynamic: requires-dist
Dynamic: requires-python
Dynamic: summary
